<!DOCTYPE codename-engine-stage>
<stage startCamPosX="600" startCamPosY="550" folder="stages/school/erect/" zoom="1" name="schoolPico">
	<use-extension script="pixel"/>

	<sprite antialiasing="false" x="-12" updateHitbox="true" scroll="0.1" sprite="weebSky" scale="6" name="bgSky"/>

	<sprite antialiasing="false" x="-100" updateHitbox="true" scroll="0.6" sprite="weebBackTrees" y="-70" scale="6" name="bgtrees2"/>

	<sprite antialiasing="false" scrolly="0.9" x="-216" updateHitbox="true" sprite="weebSchool" scale="6" scrollx="0.95" name="bgSchool"/>

	<sprite antialiasing="false" x="-204" updateHitbox="true" scroll="0.95" sprite="weebStreet" scale="6" name="bgStreet"/>

	<sprite antialiasing="false" x="-30" updateHitbox="true" scroll="0.9" sprite="weebTreesBack" y="130" scale="4.797" name="fgTrees"/>
	<sprite antialiasing="false" x="-590" updateHitbox="true" scroll="0.85" sprite="weebTrees" y="-800" scale="5.102" name="bgTrees"/>
	
	<sprite antialiasing="false" x="527.375764372023" sprite="abot/abotHead" y="723.807581315105" type="none" scale="6" name="aBot-Head"/>

	<sprite antialiasing="false" x="801.472965505639" sprite="abot/aBotPixelBack" y="680.3030703312" type="none" scale="6" name="aBot-back"/>

	<!--Viz-->

	<!--Viz Left-->

	<sprite antialiasing="false" x="670" sprite="abot/aBotVizPixel" y="705" type="loop" scale="6" name="aBot-Viz1">
		<anim name="aBot-Viz1" anim="viz1" fps="15" loop="true" playOnCountdown="false"/>
	</sprite>

	<sprite antialiasing="false" x="730" sprite="abot/aBotVizPixel" y="705" type="loop" scale="6" name="aBot-Viz2">
		<anim name="aBot-Viz2" anim="viz2" fps="16" loop="true" playOnCountdown="false"/>
	</sprite>

	<sprite antialiasing="false" x="775" sprite="abot/aBotVizPixel" y="705" type="loop" scale="6" name="aBot-Viz3">
		<anim name="aBot-Viz3" anim="viz3" fps="17" loop="true" playOnCountdown="false"/>
	</sprite>

	<!--Viz Mid-->

	<sprite antialiasing="false" x="830" sprite="abot/aBotVizPixel" y="705" type="loop" scale="6" name="aBot-Viz4">
		<anim name="aBot-Viz4" anim="viz4" fps="18" loop="true" playOnCountdown="false"/>
	</sprite>

	<!--Viz Right-->

	<sprite antialiasing="false" x="890" sprite="abot/aBotVizPixel" y="705" type="loop" scale="6" name="aBot-Viz5">
		<anim name="aBot-Viz5" anim="viz5" fps="17" loop="true" playOnCountdown="false"/>
	</sprite>

	<sprite antialiasing="false" x="930" sprite="abot/aBotVizPixel" y="705" type="loop" scale="6" name="aBot-Viz6">
		<anim name="aBot-Viz6" anim="viz6" fps="16" loop="true" playOnCountdown="false"/>
	</sprite>

	<sprite antialiasing="false" x="990" sprite="abot/aBotVizPixel" y="705" type="loop" scale="6" name="aBot-Viz7">
		<anim name="aBot-Viz7" anim="viz7" fps="15" loop="true" playOnCountdown="false"/>
	</sprite>

	<sprite antialiasing="false" x="770.684505650721" sprite="abot/aBotPixel" y="670.491850565119" type="beat" scale="6" name="aBot/Cover"/>
	<boyfriend x="1150" y="300"/>
	<girlfriend x="720" scroll="1" y="245.757359312881"/>
	<dad/>
</stage>
